carjam/__init__.py
carjam/client.py
carjam-1.0.2.post1.dist-info/LICENSE
carjam-1.0.2.post1.dist-info/METADATA
carjam-1.0.2.post1.dist-info/WHEEL
carjam-1.0.2.post1.dist-info/top_level.txt
carjam-1.0.2.post1.dist-info/RECORD
