Metadata-Version: 2.1
Name: carjam
Version: 1.0.2.post1
Summary: Unoffical Python API for CarJam NZ
Home-page: https://github.com/kianz20/CarJam-API
Author: Kian Jazayeri
Author-email: kianja02@gmail.com
Classifier: Programming Language :: Python :: 3
Classifier: License :: OSI Approved :: MIT License
Classifier: Operating System :: OS Independent
License-File: LICENSE
